{
    "questions": [
        {
            "question": "What is a flip-flop?",
            "options": ["A bistable multivibrator", "A type of resistor", "A type of capacitor", "None of the above"],
            "answer": "A bistable multivibrator"
        },
        {
            "question": "Which flip-flop is known as a data or delay flip-flop?",
            "options": ["D flip-flop", "T flip-flop", "JK flip-flop", "SR flip-flop"],
            "answer": "D flip-flop"
        },
        {
            "question": "What is the characteristic equation of a JK flip-flop?",
            "options": ["Q(next) = JQ' + K'Q", "Q(next) = JQ + KQ'", "Q(next) = JQ + K'Q'", "Q(next) = J'Q + KQ'"],
            "answer": "Q(next) = JQ' + K'Q"
        }
    ]
}
